[
{
	"description":"Clip angle shear connection",
	"type":"Beam connection",
	"code":"SC001",
	"specification":"AISC 360-2010",
	"image":"images/sc001_tmb.svg",
	"link":"sc001.php"
},	
{
	"description":"End plate moment connection (Seismic applications)",
	"type":"Beam connection",
	"code":"MC001",
	"specification":"AISC 360-2010, AISC 341",
	"image":"images/mc001_tmb.svg",
	"link":"mc001.php"
},	
{
	"description":"Horizontal bracing connection",
	"type":"Bracing connection",
	"code":"HB001",
	"specification":"AISC 360-2010",
	"image":"images/hb001_tmb.svg",
	"link":"hb001.php"
},	
{
	"description":"Beam column vertical bracing connection",
	"type":"Bracing connection",
	"code":"VB001",
	"specification":"AISC 360-2010",
	"image":"images/vb001_tmb.svg",
	"link":"vb001.php"
}

]